bayesflow/__init__.py
bayesflow/adapters/__init__.py
bayesflow/adapters/adapter.py
bayesflow/adapters/transforms/__init__.py
bayesflow/adapters/transforms/as_set.py
bayesflow/adapters/transforms/as_time_series.py
bayesflow/adapters/transforms/broadcast.py
bayesflow/adapters/transforms/concatenate.py
bayesflow/adapters/transforms/constrain.py
bayesflow/adapters/transforms/convert_dtype.py
bayesflow/adapters/transforms/drop.py
bayesflow/adapters/transforms/elementwise_transform.py
bayesflow/adapters/transforms/expand_dims.py
bayesflow/adapters/transforms/filter_transform.py
bayesflow/adapters/transforms/group.py
bayesflow/adapters/transforms/keep.py
bayesflow/adapters/transforms/log.py
bayesflow/adapters/transforms/map_transform.py
bayesflow/adapters/transforms/nan_to_num.py
bayesflow/adapters/transforms/nnpe.py
bayesflow/adapters/transforms/numpy_transform.py
bayesflow/adapters/transforms/one_hot.py
bayesflow/adapters/transforms/random_subsample.py
bayesflow/adapters/transforms/rename.py
bayesflow/adapters/transforms/scale.py
bayesflow/adapters/transforms/serializable_custom_transform.py
bayesflow/adapters/transforms/shift.py
bayesflow/adapters/transforms/split.py
bayesflow/adapters/transforms/sqrt.py
bayesflow/adapters/transforms/squeeze.py
bayesflow/adapters/transforms/standardize.py
bayesflow/adapters/transforms/take.py
bayesflow/adapters/transforms/to_array.py
bayesflow/adapters/transforms/to_dict.py
bayesflow/adapters/transforms/transform.py
bayesflow/adapters/transforms/ungroup.py
bayesflow/approximators/__init__.py
bayesflow/approximators/approximator.py
bayesflow/approximators/continuous_approximator.py
bayesflow/approximators/model_comparison_approximator.py
bayesflow/approximators/point_approximator.py
bayesflow/approximators/backend_approximators/__init__.py
bayesflow/approximators/backend_approximators/backend_approximator.py
bayesflow/approximators/backend_approximators/jax_approximator.py
bayesflow-2.0.5.dist-info/licenses/LICENSE
bayesflow-2.0.5.dist-info/METADATA
bayesflow-2.0.5.dist-info/WHEEL
bayesflow-2.0.5.dist-info/top_level.txt
bayesflow-2.0.5.dist-info/RECORD
