Metadata-Version: 2.4
Name: bayesflow
Version: 2.0.5
Summary: Amortizing Bayesian Inference With Neural Networks
Author: The BayesFlow Team
License: MIT License
Classifier: Development Status :: 5 - Production/Stable
Classifier: Intended Audience :: Science/Research
Classifier: Intended Audience :: Developers
Classifier: License :: OSI Approved :: MIT License
Classifier: Operating System :: OS Independent
Classifier: Programming Language :: Python :: 3
Classifier: Programming Language :: Python :: 3 :: Only
Classifier: Programming Language :: Python :: 3.10
Classifier: Programming Language :: Python :: 3.11
Classifier: Programming Language :: Python :: 3.12
Classifier: Topic :: Scientific/Engineering :: Artificial Intelligence
Requires-Python: <3.13,>=3.10
License-File: LICENSE
Requires-Dist: keras>=3.9
Requires-Dist: matplotlib
Requires-Dist: numpy<2.0,>=1.24
Requires-Dist: pandas
Requires-Dist: scipy
Requires-Dist: seaborn
Requires-Dist: tqdm
Provides-Extra: all
Requires-Dist: jupyter; extra == "all"
Requires-Dist: jupyterlab; extra == "all"
Requires-Dist: nbconvert; extra == "all"
Requires-Dist: ipython; extra == "all"
Requires-Dist: ipykernel; extra == "all"
Requires-Dist: pre-commit; extra == "all"
Requires-Dist: ruff; extra == "all"
Requires-Dist: tox; extra == "all"
Requires-Dist: myst-nb~=1.2; extra == "all"
Requires-Dist: numpydoc~=1.8; extra == "all"
Requires-Dist: pydata-sphinx-theme~=0.16; extra == "all"
Requires-Dist: sphinx~=8.1.3; extra == "all"
Requires-Dist: sphinx-polyversion==1.1; extra == "all"
Requires-Dist: sphinx_design~=0.6; extra == "all"
Requires-Dist: sphinxcontrib-bibtex~=2.6; extra == "all"
Requires-Dist: snowballstemmer~=2.2.0; extra == "all"
Requires-Dist: pytest; extra == "all"
Requires-Dist: pytest-cov; extra == "all"
Requires-Dist: pytest-rerunfailures; extra == "all"
Requires-Dist: pytest-xdist; extra == "all"
Provides-Extra: dev
Requires-Dist: jupyter; extra == "dev"
Requires-Dist: jupyterlab; extra == "dev"
Requires-Dist: pre-commit; extra == "dev"
Requires-Dist: ruff; extra == "dev"
Requires-Dist: tox; extra == "dev"
Provides-Extra: docs
Requires-Dist: myst-nb~=1.2; extra == "docs"
Requires-Dist: numpydoc~=1.8; extra == "docs"
Requires-Dist: pydata-sphinx-theme~=0.16; extra == "docs"
Requires-Dist: sphinx~=8.1.3; extra == "docs"
Requires-Dist: sphinx-polyversion==1.1; extra == "docs"
Requires-Dist: sphinx_design~=0.6; extra == "docs"
Requires-Dist: sphinxcontrib-bibtex~=2.6; extra == "docs"
Requires-Dist: snowballstemmer~=2.2.0; extra == "docs"
Provides-Extra: test
Requires-Dist: nbconvert; extra == "test"
Requires-Dist: ipython; extra == "test"
Requires-Dist: ipykernel; extra == "test"
Requires-Dist: pytest; extra == "test"
Requires-Dist: pytest-cov; extra == "test"
Requires-Dist: pytest-rerunfailures; extra == "test"
Requires-Dist: pytest-xdist; extra == "test"
Dynamic: license-file
